[{"idx":0,"id":"1705d43c-23fe-4ae6-8c99-51781301dbdb","user_id":"1b226b6e-a012-49fd-902e-ec9d0e8852a0","full_name":null,"phone":null,"avatar_url":"/assets/avatares/BUCK.png","points_balance":0,"segment":null,"created_at":"2025-12-02 15:56:45.465956+00","updated_at":"2025-12-07 22:31:01.310799+00","email":"silxarseb@gmail.com","first_name":"SilXarSeb","last_name":"","city":null,"avatar":"buck","address_label":null,"street":null,"number":null,"floor":null,"postal_code":null,"full_address":null,"language":"en"},{"idx":1,"id":"550a11ea-8eaf-4046-8caa-86ca9fccf657","user_id":"c3b6003b-370d-4fc8-bc53-066102af7d08","full_name":"Sebastián Gonzaaález Rebecchi","phone":"+346634923484","avatar_url":"/assets/avatares/BUCK.png","points_balance":100,"segment":"NEW","created_at":"2025-12-01 00:45:12.357+00","updated_at":"2025-12-01 03:41:45.370001+00","email":"sebaxy5270@gmail.com","first_name":null,"last_name":null,"city":null,"avatar":"buck","address_label":null,"street":null,"number":null,"floor":null,"postal_code":null,"full_address":null,"language":"es"},{"idx":2,"id":"9b8cc744-3226-416d-ac76-531728d19061","user_id":"448dd250-5535-4514-9353-5b83658f0d3a","full_name":"seba asda","phone":"65651212","avatar_url":"/assets/avatares/CANDELA.png","points_balance":0,"segment":null,"created_at":"2025-12-02 19:14:57.372954+00","updated_at":"2025-12-03 08:07:09.489107+00","email":"sebacsy58@gmail.com","first_name":"seba","last_name":"asda","city":"asdadsadsa","avatar":"buck","address_label":"asda","street":"asdadsa","number":"1","floor":null,"postal_code":"46152","full_address":"asdadsa, 1, 46152, asdadsadsa","language":"es"},{"idx":3,"id":"a064b4dd-4965-4a79-aed7-ee5fc4eec444","user_id":"ebb810a2-e482-4cef-a2b1-71600fb7d259","full_name":null,"phone":null,"avatar_url":"/assets/avatares/BUCK.png","points_balance":0,"segment":null,"created_at":"2025-12-02 23:25:45.414622+00","updated_at":"2025-12-03 06:53:02.005071+00","email":"holaaaaapruebaaa124@gmail.com","first_name":"Holaaa","last_name":"","city":null,"avatar":"buck","address_label":null,"street":null,"number":null,"floor":null,"postal_code":null,"full_address":null,"language":"es"},{"idx":4,"id":"b652dc99-0986-4016-a59b-8b6aa87fac6d","user_id":"d847a750-3099-4df9-800e-6209c99a0e84","full_name":null,"phone":null,"avatar_url":"/assets/avatares/SIFRINA.png","points_balance":0,"segment":null,"created_at":"2025-12-02 15:59:00.336773+00","updated_at":"2025-12-08 18:47:14.733803+00","email":"pruebaaaa1231vdhdh@gmail.com","first_name":"Hehrhdvc","last_name":"","city":null,"avatar":"buck","address_label":null,"street":null,"number":null,"floor":null,"postal_code":null,"full_address":null,"language":"en"},{"idx":5,"id":"dfc1b0ee-0253-47b0-ba5a-31b2033ed7ed","user_id":"13b7095d-b96a-4093-aa93-956161f62ad6","full_name":null,"phone":null,"avatar_url":null,"points_balance":0,"segment":null,"created_at":"2025-12-02 16:27:05.285301+00","updated_at":"2025-12-02 16:27:05.266+00","email":"opre8364@gmail.com","first_name":"Opre","last_name":"","city":null,"avatar":"buck","address_label":null,"street":null,"number":null,"floor":null,"postal_code":null,"full_address":null,"language":"es"},{"idx":6,"id":"e823389d-fd25-4a52-ae09-32ddf25e431f","user_id":"806ce86c-3c1c-448c-889b-15ed65f40a4c","full_name":null,"phone":"656565","avatar_url":null,"points_balance":0,"segment":null,"created_at":"2025-12-03 10:06:53.744656+00","updated_at":"2025-12-03 10:06:53.855022+00","email":"hola@hola.com","first_name":"sdasd","last_name":"sdasda","city":"valencia","avatar":"buck","address_label":null,"street":null,"number":null,"floor":null,"postal_code":null,"full_address":", valencia","language":"es"}]